chemsys/__init__.py
chemsys/chemsystestn.py
chemsys/chemsystestpdflatex.py
chemsys/cs.py
chemsys/csg.py
chemsys/cspdf.py
chemsys/cst.py
chemsys/cstest.py
chemsys-1.0.49.dist-info/LICENSE.txt
chemsys-1.0.49.dist-info/METADATA
chemsys-1.0.49.dist-info/WHEEL
chemsys-1.0.49.dist-info/top_level.txt
chemsys-1.0.49.dist-info/RECORD
